odoo/addons/website_form_recaptcha/README.rst
odoo/addons/website_form_recaptcha/__init__.py
odoo/addons/website_form_recaptcha/__manifest__.py
odoo/addons/website_form_recaptcha/controllers/__init__.py
odoo/addons/website_form_recaptcha/controllers/main.py
odoo/addons/website_form_recaptcha/i18n/af.po
odoo/addons/website_form_recaptcha/i18n/am.po
odoo/addons/website_form_recaptcha/i18n/ar.po
odoo/addons/website_form_recaptcha/i18n/bg.po
odoo/addons/website_form_recaptcha/i18n/bs.po
odoo/addons/website_form_recaptcha/i18n/ca.po
odoo/addons/website_form_recaptcha/i18n/cs.po
odoo/addons/website_form_recaptcha/i18n/da.po
odoo/addons/website_form_recaptcha/i18n/de.po
odoo/addons/website_form_recaptcha/i18n/el.po
odoo/addons/website_form_recaptcha/i18n/el_GR.po
odoo/addons/website_form_recaptcha/i18n/en_GB.po
odoo/addons/website_form_recaptcha/i18n/es.po
odoo/addons/website_form_recaptcha/i18n/es_AR.po
odoo/addons/website_form_recaptcha/i18n/es_CL.po
odoo/addons/website_form_recaptcha/i18n/es_CO.po
odoo/addons/website_form_recaptcha/i18n/es_CR.po
odoo/addons/website_form_recaptcha/i18n/es_DO.po
odoo/addons/website_form_recaptcha/i18n/es_EC.po
odoo/addons/website_form_recaptcha/i18n/es_ES.po
odoo/addons/website_form_recaptcha/i18n/es_MX.po
odoo/addons/website_form_recaptcha/i18n/es_PE.po
odoo/addons/website_form_recaptcha/i18n/es_PY.po
odoo/addons/website_form_recaptcha/i18n/es_VE.po
odoo/addons/website_form_recaptcha/i18n/et.po
odoo/addons/website_form_recaptcha/i18n/eu.po
odoo/addons/website_form_recaptcha/i18n/fa.po
odoo/addons/website_form_recaptcha/i18n/fi.po
odoo/addons/website_form_recaptcha/i18n/fr.po
odoo/addons/website_form_recaptcha/i18n/fr_CA.po
odoo/addons/website_form_recaptcha/i18n/fr_CH.po
odoo/addons/website_form_recaptcha/i18n/gl.po
odoo/addons/website_form_recaptcha/i18n/gl_ES.po
odoo/addons/website_form_recaptcha/i18n/he.po
odoo/addons/website_form_recaptcha/i18n/hr.po
odoo/addons/website_form_recaptcha/i18n/hr_HR.po
odoo12_addon_website_form_recaptcha-12.0.1.2.5.dist-info/METADATA
odoo12_addon_website_form_recaptcha-12.0.1.2.5.dist-info/WHEEL
odoo12_addon_website_form_recaptcha-12.0.1.2.5.dist-info/top_level.txt
odoo12_addon_website_form_recaptcha-12.0.1.2.5.dist-info/RECORD
